usiq/__init__.py
usiq/cli.py
usiq/parser.py
usiq/renamer.py
usiq/tagger.py
usiq-64.0.data/scripts/usiq
usiq-64.0.dist-info/DESCRIPTION.rst
usiq-64.0.dist-info/METADATA
usiq-64.0.dist-info/RECORD
usiq-64.0.dist-info/WHEEL
usiq-64.0.dist-info/metadata.json
usiq-64.0.dist-info/namespace_packages.txt
usiq-64.0.dist-info/top_level.txt
usiq-64.0.dist-info/zip-safe
