Metadata-Version: 2.0
Name: usiq
Version: 64.0
Summary: UNKNOWN
Home-page: UNKNOWN
Author: UNKNOWN
Author-email: UNKNOWN
License: UNKNOWN
Platform: UNKNOWN
Classifier: Development Status :: 3 - Alpha
Classifier: Programming Language :: Python
Requires-Dist: docopt
Requires-Dist: logbook
Requires-Dist: mutagen
Requires-Dist: pyyaml
